google/cloud/maintenance_api/__init__.py
google/cloud/maintenance_api/gapic_version.py
google/cloud/maintenance_api/py.typed
google/cloud/maintenance_api_v1/__init__.py
google/cloud/maintenance_api_v1/gapic_metadata.json
google/cloud/maintenance_api_v1/gapic_version.py
google/cloud/maintenance_api_v1/py.typed
google/cloud/maintenance_api_v1/services/__init__.py
google/cloud/maintenance_api_v1/services/maintenance/__init__.py
google/cloud/maintenance_api_v1/services/maintenance/async_client.py
google/cloud/maintenance_api_v1/services/maintenance/client.py
google/cloud/maintenance_api_v1/services/maintenance/pagers.py
google/cloud/maintenance_api_v1/services/maintenance/transports/__init__.py
google/cloud/maintenance_api_v1/services/maintenance/transports/base.py
google/cloud/maintenance_api_v1/services/maintenance/transports/grpc.py
google/cloud/maintenance_api_v1/services/maintenance/transports/grpc_asyncio.py
google/cloud/maintenance_api_v1/services/maintenance/transports/rest.py
google/cloud/maintenance_api_v1/services/maintenance/transports/rest_base.py
google/cloud/maintenance_api_v1/types/__init__.py
google/cloud/maintenance_api_v1/types/maintenance_service.py
google/cloud/maintenance_api_v1beta/__init__.py
google/cloud/maintenance_api_v1beta/gapic_metadata.json
google/cloud/maintenance_api_v1beta/gapic_version.py
google/cloud/maintenance_api_v1beta/py.typed
google/cloud/maintenance_api_v1beta/services/__init__.py
google/cloud/maintenance_api_v1beta/services/maintenance/__init__.py
google/cloud/maintenance_api_v1beta/services/maintenance/async_client.py
google/cloud/maintenance_api_v1beta/services/maintenance/client.py
google/cloud/maintenance_api_v1beta/services/maintenance/pagers.py
google/cloud/maintenance_api_v1beta/services/maintenance/transports/__init__.py
google/cloud/maintenance_api_v1beta/services/maintenance/transports/base.py
google/cloud/maintenance_api_v1beta/services/maintenance/transports/grpc.py
google_cloud_maintenance_api-0.3.0.dist-info/licenses/LICENSE
google_cloud_maintenance_api-0.3.0.dist-info/METADATA
google_cloud_maintenance_api-0.3.0.dist-info/WHEEL
google_cloud_maintenance_api-0.3.0.dist-info/top_level.txt
google_cloud_maintenance_api-0.3.0.dist-info/RECORD
